mcp_server_imessage/AddressBook.py
mcp_server_imessage/SnowflakeComponents.py
mcp_server_imessage/__init__.py
mcp_server_imessage/__main__.py
mcp_server_imessage/iMessage.py
mcp_server_imessage/server.py
mcp_server_imessage/errors/__init__.py
mcp_server_imessage/models/__init__.py
mcp_server_imessage/models/base.py
mcp_server_imessage/models/chat.py
mcp_server_imessage/models/handle.py
mcp_server_imessage/models/message.py
mcp_server_imessage-0.0.1.dist-info/LICENSE
mcp_server_imessage-0.0.1.dist-info/METADATA
mcp_server_imessage-0.0.1.dist-info/WHEEL
mcp_server_imessage-0.0.1.dist-info/top_level.txt
mcp_server_imessage-0.0.1.dist-info/RECORD
